{
  "type": "Feature",
  "properties": {
    "iso:country":"SE",
    "sg:address":"Kungsgatan 6",
    "sg:city":"Stockholm",
    "sg:classifiers":[
        {
            "category":"Professional",
            "subcategory":"Computer Services",
            "type":"Services"
        }
    ],
    "sg:postcode":"SE-111 43 ",
    "sg:website":"http://www.lbi.com/",
    "wof:name":"LBI International",
    "wof:placetype":"venue"
},
  "geometry": {"coordinates":[18.061249,59.335028],"type":"Point"}
}