{
  "type": "Feature",
  "properties": {
    "iso:country":"SE",
    "sg:address":"\u00d6ster\u00f6gatan 1-3",
    "sg:city":"Kista",
    "sg:classifiers":[
        {
            "category":"Professional",
            "subcategory":"Computer Services",
            "type":"Services"
        }
    ],
    "sg:postcode":"164 40",
    "sg:website":"http://www.byteactive.com",
    "wof:name":"ByteActive",
    "wof:placetype":"venue"
},
  "geometry": {"coordinates":[17.9619066,59.4019568],"type":"Point"}
}