{
  "type": "Feature",
  "properties": {
    "iso:country":"SE",
    "sg:address":"Framtidsv\u00e4gen 10A Vid\u00e9um Science Park",
    "sg:city":"V\u00e4xj\u00f6",
    "sg:classifiers":[
        {
            "category":"Professional",
            "subcategory":"Computer Services",
            "type":"Services"
        }
    ],
    "sg:postcode":"351 06",
    "sg:website":"http://www.fortnox.se",
    "wof:name":"Fortnox",
    "wof:placetype":"venue"
},
  "geometry": {"coordinates":[14.8248671,56.8559617],"type":"Point"}
}