{
  "type": "Feature",
  "properties": {
    "iso:country":"SE",
    "sg:address":"Arvid Wallgrens Backe 20",
    "sg:city":"Gothenburg",
    "sg:classifiers":[
        {
            "category":"Professional",
            "subcategory":"Research",
            "type":"Services"
        }
    ],
    "sg:postcode":"413 46",
    "sg:website":"http://www.albireopharma.com",
    "wof:name":"Albireo",
    "wof:placetype":"venue"
},
  "geometry": {"coordinates":[11.955296,57.6857201],"type":"Point"}
}