{
  "type": "Feature",
  "properties": {
    "iso:country":"SE",
    "sg:address":"Fogdevreten 2, Solna",
    "sg:city":"Stockholm",
    "sg:classifiers":[
        {
            "category":"Professional",
            "subcategory":"Research",
            "type":"Services"
        }
    ],
    "sg:postcode":"S-171 77",
    "wof:name":"Karolinska",
    "wof:placetype":"venue"
},
  "geometry": {"coordinates":[18.0200968,59.351153],"type":"Point"}
}