{
  "type": "Feature",
  "properties": {
    "iso:country":"SE",
    "sg:address":"Torshamnsgatan 39",
    "sg:city":"Kista",
    "sg:classifiers":[
        {
            "category":"Manufacturing",
            "subcategory":"Electronics",
            "type":"Manufacturing & Wholesale Goods"
        }
    ],
    "sg:postcode":"SE-164 40",
    "sg:website":"http://www.nanoradio.com/",
    "wof:name":"Nanoradio",
    "wof:placetype":"venue"
},
  "geometry": {"coordinates":[17.9514708,59.4074153],"type":"Point"}
}